django_kaio-1.7.0.dist-info/licenses/LICENSE
kaio/__init__.py
kaio/debug_toolbar.py
kaio/options.py
kaio/properties.py
kaio/management/__init__.py
kaio/management/commands/__init__.py
kaio/management/commands/generate_ini.py
kaio/management/commands/kaiosettings.py
kaio/mixins/__init__.py
kaio/mixins/cache.py
kaio/mixins/celeryconf.py
kaio/mixins/cms.py
kaio/mixins/compress.py
kaio/mixins/database.py
kaio/mixins/debug.py
kaio/mixins/email.py
kaio/mixins/filerconf.py
kaio/mixins/logs.py
kaio/mixins/paths.py
kaio/mixins/security.py
kaio/mixins/sentry.py
kaio/mixins/storage.py
kaio/mixins/whitenoise.py
django_kaio-1.7.0.dist-info/METADATA
django_kaio-1.7.0.dist-info/WHEEL
django_kaio-1.7.0.dist-info/top_level.txt
django_kaio-1.7.0.dist-info/RECORD
